astro_scripts/CRIRES2ARES.py
astro_scripts/SWEETCat.py
astro_scripts/VALDextraction.py
astro_scripts/VALDprepare.py
astro_scripts/__about__.py
astro_scripts/__init__.py
astro_scripts/ascii2fits.py
astro_scripts/fitsHeader.py
astro_scripts/linelist_filter.py
astro_scripts/numpy2moog.py
astro_scripts/plot_fits.py
astro_scripts/plot_fits_cli.py
astro_scripts/rv_measure.py
astro_scripts/vizier_query.py
astro_scripts/vizier_query_cli.py
astro_scripts-0.1.0.dist-info/DESCRIPTION.rst
astro_scripts-0.1.0.dist-info/METADATA
astro_scripts-0.1.0.dist-info/RECORD
astro_scripts-0.1.0.dist-info/WHEEL
astro_scripts-0.1.0.dist-info/entry_points.txt
astro_scripts-0.1.0.dist-info/metadata.json
astro_scripts-0.1.0.dist-info/top_level.txt
