Metadata-Version: 2.0
Name: astro-scripts
Version: 0.1.0
Summary: Small scripts for astronomy
Home-page: https://github.com/DanielAndreasen/astro_scripts
Author: Daniel T. Andreasen
Author-email: daniel.andreasen@astro.up.pt
License: MIT
Keywords: astronomy,spectra,spectroscopy
Platform: UNKNOWN
Classifier: Development Status :: 3 - Alpha
Classifier: Intended Audience :: Science/Research
Classifier: Topic :: Scientific/Engineering :: Astronomy
Classifier: Topic :: Scientific/Engineering :: Physics
Classifier: License :: OSI Approved :: MIT License
Classifier: Programming Language :: Python :: 2
Classifier: Programming Language :: Python :: 2.7
Classifier: Natural Language :: English
Requires-Dist: astropy
Requires-Dist: gooey
Requires-Dist: matplotlib
Requires-Dist: numpy
Requires-Dist: pandas
Requires-Dist: pyastronomy
Requires-Dist: requests
Requires-Dist: scipy
Provides-Extra: dev
Requires-Dist: check-manifest; extra == 'dev'
Provides-Extra: docs
Requires-Dist: pyastronomy; extra == 'docs'
Requires-Dist: sphinx (>=1.4); extra == 'docs'
Requires-Dist: sphinx-rtd-theme; extra == 'docs'
Provides-Extra: test
Requires-Dist: coverage; extra == 'test'
Requires-Dist: hypothesis; extra == 'test'
Requires-Dist: pytest; extra == 'test'
Requires-Dist: pytest-cov; extra == 'test'
Requires-Dist: python-coveralls; extra == 'test'
